quadprog.cpython-38-x86_64-linux-gnu.so
quadprog_wheel-0.1.11.dist-info/WHEEL
quadprog_wheel-0.1.11.dist-info/RECORD
quadprog_wheel-0.1.11.dist-info/METADATA
quadprog_wheel-0.1.11.dist-info/LICENSE
quadprog_wheel-0.1.11.dist-info/top_level.txt
