Metadata-Version: 2.1
Name: quadprog-wheel
Version: 0.1.11
Summary: Quadratic Programming Solver with wheel packages
Home-page: https://github.com/quadprog/quadprog
Author: Robert T. McGibbon
Author-email: rmcgibbo@gmail.com
License: GPLv2+
Classifier: Development Status :: 3 - Alpha
Classifier: Intended Audience :: Education
Classifier: Intended Audience :: Financial and Insurance Industry
Classifier: Intended Audience :: Science/Research
Classifier: License :: OSI Approved :: GNU General Public License v2 or later (GPLv2+)
Classifier: Programming Language :: Python :: 3
Classifier: Programming Language :: Python :: 3.6
Classifier: Programming Language :: Python :: 3.7
Classifier: Programming Language :: Python :: 3.8
Classifier: Programming Language :: Python :: 3.9
Classifier: Programming Language :: Python :: 3.10
Classifier: Topic :: Scientific/Engineering :: Mathematics
Requires-Python: >=3.6, <3.11
License-File: LICENSE
Requires-Dist: numpy
